browseon/__init__.py
browseon/__main__.py
browseon/search.py
browseon/util.py
browseon-1.0.0.dist-info/METADATA
browseon-1.0.0.dist-info/WHEEL
browseon-1.0.0.dist-info/entry_points.txt
browseon-1.0.0.dist-info/top_level.txt
browseon-1.0.0.dist-info/RECORD
