Metadata-Version: 2.1
Name: browseon
Version: 1.0.0
Summary: To browse web.
Author-email: srg <srg.code@pm.me>
License: Apache License, Version 2.0
Project-URL: Homepage, https://github.com/codesrg/browseon
Project-URL: Bug Tracker, https://github.com/codesrg/browseon/issues
Keywords: browseon,web search
Classifier: Programming Language :: Python :: 3
Classifier: License :: OSI Approved :: Apache Software License
Classifier: Operating System :: OS Independent
Requires-Python: >=3.6
Requires-Dist: srutil
